LICENSE.txt
README.md
setup.cfg
setup.py
synochatinfo/__init__.py
synochatinfo/synochat.py
synochatinfo/tempCodeRunnerFile.py
synochatinfo.egg-info/PKG-INFO
synochatinfo.egg-info/SOURCES.txt
synochatinfo.egg-info/dependency_links.txt
synochatinfo.egg-info/requires.txt
synochatinfo.egg-info/top_level.txt