Metadata-Version: 2.1
Name: synochatinfo
Version: 0.0.0.0.2
Summary: Bug fixed hopefully
Home-page: https://github.com/sushil3125/Spam-Bot-using-Python
Download-URL: https://github.com/sushil3125/Spam-Bot-using-Python/blob/main/projectSpamBot.exe
Author: knightmare
Author-email: kneel.stha@gmail.com
License: MIT
Classifier: Programming Language :: Python :: 3
Classifier: Programming Language :: Python :: 3.4
Classifier: Programming Language :: Python :: 3.5
Classifier: Programming Language :: Python :: 3.6
License-File: LICENSE.txt
